setup.py
game_ttt/__init__.py
game_ttt/game_ttt.py
game_ttt.egg-info/PKG-INFO
game_ttt.egg-info/SOURCES.txt
game_ttt.egg-info/dependency_links.txt
game_ttt.egg-info/top_level.txt