Metadata-Version: 1.0
Name: game-ttt
Version: 0.3
Summary: play the game tic_tac_toe
Home-page: UNKNOWN
Author: Dhiraj Kumar Chaudhary
Author-email: dhirajc963@gmail.com
License: UNKNOWN
Platform: UNKNOWN
